{
  "data": [
    {
      "contentsUrl": "https://i.etsystatic.com/10204022/c/2479/1970/243/466/il/ebecb4/2981833988/il_340x270.2981833988_6sg5.jpg",
      "price": 33.6,
      "discount": 0,
      "freeShipping": false,
      "title": "Personailized name Necklace by CaitlynMinimalist gold name necklace with box chain",
      "reviews": 250177
    },
    {
      "contentsUrl": "https://i.etsystatic.com/10204022/c/2479/1970/243/466/il/ebecb4/2981833988/il_340x270.2981833988_6sg5.jpg",
      "price": 49.98,
      "discount": 60,
      "freeShipping": false,
      "title": "Valentines Day Gift for Him,Personalized Wallet,Mens Wallet,Engraved Wallet,Leather Wallet,Custom Wallet,Boyfriend Gift for Men,Gift for Dad",
      "reviews": 20346
    },
    {
      "contentsUrl": "https://i.etsystatic.com/27890741/c/2126/1690/163/299/il/9a051c/3412471944/il_340x270.3412471944_tcbv.jpg",
      "price": 17,
      "discount": 40,
      "freeShipping": false,
      "title": "Fidget Slug Articulating Stim Toy | Largest selection of colors, types and sizes anywhere | Shipped same day",
      "reviews": 4306
    },
    {
      "contentsUrl": "https://i.etsystatic.com/10204022/c/2479/1970/243/466/il/ebecb4/2981833988/il_340x270.2981833988_6sg5.jpg",
      "price": 13.45,
      "discount": 50,
      "freeShipping": false,
      "title": "Custom Name Necklace with Birth Flower,Dainty Personalized Minimalist Jewelry,Pendant Necklace for Women,Christmas Bridesmaid Gift for Her",
      "reviews": 5771
    },
    {
      "contentsUrl": "https://i.etsystatic.com/27890741/c/2126/1690/163/299/il/9a051c/3412471944/il_340x270.3412471944_tcbv.jpg",
      "price": 16.97,
      "discount": 50,
      "freeShipping": false,
      "title": "Heart Keychain Set - Made with Authentic LEGO® Bricks, Matching Friendship keychains, Gift for Couples, BFFs - Very High Quality &amp; DURABLE",
      "reviews": 3287
    }
  ]
}
